{"modifiedDate":"2024-03-07T11:00:30Z","activityEntities":["trainingDataAdded",[{"title":"Training Data Added","subtitle":"BetterRest.csv","createdDate":"2024-03-07T10:58:54Z","event":"trainingDataAdded","id":"603C3EFE-EA31-46A5-8779-45418F83FE14"}],"trainingStarted",[{"subtitle":"MyTabularRegressor 1","createdDate":"2024-03-07T11:00:14Z","event":"trainingStarted","id":"A3DBFFE8-5B3C-4200-B30F-2E25016CCB67","title":"Training Started"}],"trainingFinished",[{"event":"trainingFinished","createdDate":"2024-03-07T11:00:14Z","title":"Training Completed","subtitle":"MyTabularRegressor 1","id":"E78F05F1-EFC1-43EC-981D-765BE78CBF0B"}],"experimentCreated",[{"id":"63DC20ED-300E-4B57-BFB2-61F929C71C21","title":"Model Source Created","createdDate":"2024-03-07T10:56:39Z","event":"experimentCreated","subtitle":"MyTabularRegressor 1"}]],"snapshotRole":{"withoutSnapshots":0},"id":"A3E99419-09D9-48B5-834D-557CC6AC745A","version":"1.0","settingEntity":{"algorithmType":"maxEnt","generalRegressorType":{"auto":{}},"handActionClassifierAugmentations":[],"handPoseClassifierAugmentations":[],"suggestedColumns":["wake","estimatedSleep","coffee","actualSleep"],"styleTransferAlgorithmType":"image","featureNames":["wake","estimatedSleep","coffee"],"seedType":"default","suggestedColumnValues":["31,500, 32,400, 26,100, 40,500, 19,800, 27,000, 20,700, 21,600, 41,400, 34,200, 21,600, 78,300, 32,400, 28,800, 18,900, 18,000, 28,800, 18,000, 7,200, 35,100, 24,300, 35,100, 34,200, 27,900, 30,600, 69,300, 35,100, 34,200, 34,200, 23,400","9.00, 5.00, 6.50, 8.75, 6.00, 7.50, 9.25, 6.00, 9.25, 6.75, 5.25, 9.25, 10.00, 8.75, 8.25, 6.25, 10.00, 6.25, 10.00, 9.50, 5.00, 7.50, 6.25, 8.00, 8.00, 6.50, 8.00, 10.00, 8.25, 8.00","6, 2, 10, 4, 3, 1, 1, 3, 5, 8, 3, 8, 2, 3, 1, 2, 3, 2, 1, 4, 2, 1, 1, 4, 3, 7, 4, 4, 1, 3","38,230, 20,180, 31,989, 35,258, 24,487, 28,300, 34,548, 24,557, 37,836, 31,340, 21,874, 40,405, 38,076, 34,265, 30,936, 24,665, 39,007, 24,578, 37,267, 37,878, 20,220, 28,400, 23,882, 32,427, 31,699, 29,670, 32,789, 39,792, 30,935, 31,701"],"transferLearningEmbeddingType":"dynamic","targetColumn":"actualSleep","harVideoAugmentations":0,"taskType":"generalRegresor","augmentations":[],"suggestedColumnTypes":["Int","Double","Int","Int"]},"modelEntity":{"title":"","modelURL":"Models\/MyTabularRegressor%201.mlmodel","createdDate":"2024-03-07T10:56:39Z","preferredFilename":"","version":"1.0","modifiedDate":"2024-03-07T10:56:39Z","experimentID":"A3E99419-09D9-48B5-834D-557CC6AC745A","id":"3A4C125B-79ED-43C7-8A8F-2E019F2D5ED7"},"evaluationState":"uninitialized","title":"MyTabularRegressor 1","evaluationEntity":{"id":"94978b23-5f82-49e4-904f-bf3a71366bac","dataResult":{},"analysedDataType":"none"},"trainingEntity":{"featureExtractionCheckpointMayBeAvailable":false,"trainingAccuracy":177.06208892898567,"validationAccuracy":176.87807805762287,"snapshottableCheckpoints":{},"finishTime":"2024-03-07T11:00:14Z","trainingResults":{"generalRegressor":{"maximumError":700.7884351177563,"rootMeanSquaredError":177.06208892898567}},"dataSourceID":"4184A08A-78B1-424C-9ED2-02D7092923D4","dataResult":{"itemsCount":10000,"targetRange":[19216,45224],"dataAnalysis":{"regressorAnalysis":{"targetRange":[19216,45224]},"issues":[{"severity":"info","description":"Data has 10000 rows"}],"classifierAnalysis":{},"summary":{"sampleCount":10000,"canUseValidation":1}},"columnValues":["31,500, 32,400, 26,100, 40,500, 19,800, 27,000, 20,700, 21,600, 41,400, 34,200, 21,600, 78,300, 32,400, 28,800, 18,900, 18,000, 28,800, 18,000, 7,200, 35,100, 24,300, 35,100, 34,200, 27,900, 30,600, 69,300, 35,100, 34,200, 34,200, 23,400","9.00, 5.00, 6.50, 8.75, 6.00, 7.50, 9.25, 6.00, 9.25, 6.75, 5.25, 9.25, 10.00, 8.75, 8.25, 6.25, 10.00, 6.25, 10.00, 9.50, 5.00, 7.50, 6.25, 8.00, 8.00, 6.50, 8.00, 10.00, 8.25, 8.00","6, 2, 10, 4, 3, 1, 1, 3, 5, 8, 3, 8, 2, 3, 1, 2, 3, 2, 1, 4, 2, 1, 1, 4, 3, 7, 4, 4, 1, 3","38,230, 20,180, 31,989, 35,258, 24,487, 28,300, 34,548, 24,557, 37,836, 31,340, 21,874, 40,405, 38,076, 34,265, 30,936, 24,665, 39,007, 24,578, 37,267, 37,878, 20,220, 28,400, 23,882, 32,427, 31,699, 29,670, 32,789, 39,792, 30,935, 31,701"],"columns":["wake","estimatedSleep","coffee","actualSleep"],"dataURL":"file:\/\/\/Users\/hirenrafaliya\/Downloads\/BetterRest.csv","createdDate":"2024-03-07T10:58:41Z","dataSourceID":"4184A08A-78B1-424C-9ED2-02D7092923D4","columnTypes":["Int","Double","Int","Int"]},"checkpointMetrics":{},"startTime":"2024-03-07T11:00:14Z","analysedDataType":"datasource","validationResults":{"generalRegressor":{"maximumError":694.8439790218545,"rootMeanSquaredError":176.87807805762287}},"progress":[]},"state":"trained","evaluationContainerEntity":{"modifiedDate":"2024-03-07T11:00:30Z","id":"cdb7fe63-c3a9-42f3-b9cc-f6fa9e5a8881","validationEvaluationEntity":{"evaluationResult":{"generalRegressor":{"rootMeanSquaredError":176.87807805762287,"maximumError":694.8439790218545}},"dataResult":{"createdDate":"2024-03-07T10:58:41Z"},"id":"b82e3476-12d9-421b-bfc6-480cfd9f1fc2","analysedDataType":"auto","createdDate":"2024-03-07T10:56:39Z"},"evaluationEntities":[{"dataResult":{},"analysedDataType":"none","id":"e84efa4e-7060-46d0-9e18-c8074dcc5dc1","createdDate":"2024-03-07T11:00:30Z"}],"trainingEvaluationEntity":{"id":"3861ced9-d22d-484a-8e7e-f53f84158a47","dataResult":{"createdDate":"2024-03-07T10:58:41Z","dataURL":"file:\/\/\/Users\/hirenrafaliya\/Downloads\/BetterRest.csv","itemsCount":10000,"dataSourceID":"4184A08A-78B1-424C-9ED2-02D7092923D4","dataAnalysis":{"issues":[{"severity":"info","description":"Data has 10000 rows"}],"classifierAnalysis":{},"regressorAnalysis":{"targetRange":[19216,45224]},"summary":{"sampleCount":10000,"canUseValidation":1}},"targetRange":[19216,45224]},"dataSourceID":"4184A08A-78B1-424C-9ED2-02D7092923D4","analysedDataType":"none","evaluationResult":{"generalRegressor":{"rootMeanSquaredError":177.06208892898567,"maximumError":700.7884351177563}},"createdDate":"2024-03-07T10:56:39Z"},"testingEvaluationEntity":{"dataResult":{"createdDate":"2024-03-07T10:58:41Z"},"id":"de823c25-0f3a-4570-a46c-0971da3298fb","analysedDataType":"none","createdDate":"2024-03-07T10:56:39Z"},"previewType":"tabularRegressor","createdDate":"2024-03-07T11:00:30Z"},"contentDataResult":{"createdDate":"2024-03-07T10:58:41Z"},"preferredFilename":"MyTabularRegressor 1","createdDate":"2024-03-07T10:56:39Z","validationEntity":{"dataResult":{"createdDate":"2024-03-07T10:58:41Z"},"analysedDataType":"auto"}}